typing_extensions-stubs/METADATA.toml
typing_extensions-stubs/__init__.pyi
types_typing_extensions-3.7.3.dist-info/METADATA
types_typing_extensions-3.7.3.dist-info/WHEEL
types_typing_extensions-3.7.3.dist-info/top_level.txt
types_typing_extensions-3.7.3.dist-info/RECORD
