Metadata-Version: 2.1
Name: types-typing-extensions
Version: 3.7.3
Summary: Typing stubs for typing-extensions
Home-page: https://github.com/python/typeshed
License: UNKNOWN
Platform: UNKNOWN
Classifier: Typing :: Typed
